poetry_workspaces_plugin/__init__.py
poetry_workspaces_plugin/commands/__init__.py
poetry_workspaces_plugin/commands/add.py
poetry_workspaces_plugin/commands/base.py
poetry_workspaces_plugin/commands/build.py
poetry_workspaces_plugin/commands/install.py
poetry_workspaces_plugin/commands/remove.py
poetry_workspaces_plugin/commands/tests/__init__.py
poetry_workspaces_plugin/commands/tests/test_add.py
poetry_workspaces_plugin/commands/tests/test_workspaces_list.py
poetry_workspaces_plugin/commands/workspace.py
poetry_workspaces_plugin/commands/workspaces_list.py
poetry_workspaces_plugin/config.py
poetry_workspaces_plugin/constants.py
poetry_workspaces_plugin/context.py
poetry_workspaces_plugin/factory.py
poetry_workspaces_plugin/merge.py
poetry_workspaces_plugin/plugin.py
poetry_workspaces_plugin/pyproject.py
poetry_workspaces_plugin/utils.py
poetry_workspaces_plugin-0.1.4.dist-info/METADATA
poetry_workspaces_plugin-0.1.4.dist-info/WHEEL
poetry_workspaces_plugin-0.1.4.dist-info/entry_points.txt
poetry_workspaces_plugin-0.1.4.dist-info/licenses/LICENSE
poetry_workspaces_plugin-0.1.4.dist-info/RECORD
